Metadata-Version: 2.1
Name: odoo-addon-stock_request_submit
Version: 18.0.1.0.0.2
Requires-Python: >=3.10
Requires-Dist: odoo-addon-stock_request==18.0.*
Requires-Dist: odoo==18.0.*
Summary: Add submit state on Stock Requests
Home-page: https://github.com/OCA/stock-logistics-request
License: LGPL-3
Author: Open Source Integrators, Odoo Community Association (OCA)
Author-email: support@odoo-community.org
Classifier: Programming Language :: Python
Classifier: Framework :: Odoo
Classifier: Framework :: Odoo :: 18.0
Classifier: License :: OSI Approved :: GNU Lesser General Public License v3 (LGPLv3)
